setup.cfg
setup.py
box/__init__.py
box/client.py
box.py.egg-info/PKG-INFO
box.py.egg-info/SOURCES.txt
box.py.egg-info/dependency_links.txt
box.py.egg-info/not-zip-safe
box.py.egg-info/requires.txt
box.py.egg-info/top_level.txt