Metadata-Version: 1.1
Name: box.py
Version: 1.0
Summary: Python client for Box
Home-page: http://github.com/sookasa/box.py
Author: Sookasa
Author-email: dev@sookasa.com
License: BSD
Platform: UNKNOWN
Classifier: Intended Audience :: Developers
Classifier: Operating System :: OS Independent
Classifier: Topic :: Software Development
Classifier: Programming Language :: Python
Classifier: Programming Language :: Python :: 2.7
